[
  {
    "concept_id": 135,
    "concept_name": "squared bias",
    "facts": [
      {
        "fact_text": "The bias term is the squared difference between the true mean f(x0) and the expected value of the estimate\u2014[ET (\u02c6fk(x0)) \u2212f(x0)]2\u2014where the expectation averages the randomness in the training data.",
        "fact_type": "definition",
        "importance_rank": 1,
        "paragraph_id": 4472,
        "page_number": 55
      },
      {
        "fact_text": "The second and third terms are under our control, and make up the mean squared error of \u02c6fk(x0) in estimating f(x0), which is broken down into a bias component and a variance component.",
        "fact_type": "property",
        "importance_rank": 2,
        "paragraph_id": 4472,
        "page_number": 55
      },
      {
        "fact_text": "More generally, as the model complexity of our procedure is increased, the variance tends to increase and the squared bias tends to decreases.",
        "fact_type": "property",
        "importance_rank": 3,
        "paragraph_id": 4481,
        "page_number": 56
      },
      {
        "fact_text": "This term will most likely increase with k, if the true function is reasonably smooth. For small k the few closest neighbors will have values f(x(\u2113)) close to f(x0), so their average should",
        "fact_type": "intuition",
        "importance_rank": 4,
        "paragraph_id": 4472,
        "page_number": 55
      },
      {
        "fact_text": "The expected prediction error at x0, also known as test or generalization error, can be decomposed:",
        "fact_type": "property",
        "importance_rank": 5,
        "paragraph_id": 4464,
        "page_number": 55
      },
      {
        "fact_text": "if the model is not complex enough, it will underfit and may have large bias, again resulting in poor generalization.",
        "fact_type": "intuition",
        "importance_rank": 6,
        "paragraph_id": 4481,
        "page_number": 56
      }
    ]
  },
  {
    "concept_id": 139,
    "concept_name": "orthogonal projection",
    "facts": [
      {
        "fact_text": "The p \u00d7 p matrix Hq = VqVT\nq is a projection matrix, and maps each point xi onto its rank-q reconstruction Hqxi, the orthogonal projection of xi onto the subspace spanned by the columns of Vq.",
        "fact_type": "definition",
        "importance_rank": 1,
        "paragraph_id": 39679,
        "page_number": 553
      },
      {
        "fact_text": "The penalty becomes J(f) = \u2225P1f\u2225, where P1 is the orthogonal projection of f onto H1.",
        "fact_type": "formula",
        "importance_rank": 2,
        "paragraph_id": 21589,
        "page_number": 188
      },
      {
        "fact_text": "ICA applied to multivariate data looks for a sequence of orthogonal projections such that the projected data look as far from",
        "fact_type": "property",
        "importance_rank": 3,
        "paragraph_id": 42205,
        "page_number": 580
      },
      {
        "fact_text": "A linear regression model assumes that the regression function E(Y |X) is linear in the inputs X1, . . . , Xp.",
        "fact_type": "definition",
        "importance_rank": 4,
        "paragraph_id": 4520,
        "page_number": 61
      }
    ]
  },
  {
    "concept_id": 143,
    "concept_name": "leaps and bounds procedure",
    "facts": [
      {
        "fact_text": "Best subset regression finds for each k \u2208{0, 1, 2, . . . , p} the subset of size k that gives smallest residual sum of squares (3.2). An efficient algorithm\u2014the leaps and bounds procedure (Furnival and Wilson, 1974)\u2014makes this feasible for p as large as 30 or 40.",
        "fact_type": "definition",
        "importance_rank": 1,
        "paragraph_id": 4767,
        "page_number": 75
      },
      {
        "fact_text": "The best-subset curve (red lower boundary in Figure 3.5) is necessarily decreasing, so cannot be used to select the subset size k.",
        "fact_type": "property",
        "importance_rank": 2,
        "paragraph_id": 4767,
        "page_number": 75
      },
      {
        "fact_text": "The question of how to choose k involves the tradeoff between bias and variance, along with the more subjective desire for parsimony.",
        "fact_type": "intuition",
        "importance_rank": 3,
        "paragraph_id": 4767,
        "page_number": 75
      },
      {
        "fact_text": "Note that the best subset of size 2, for example, need not include the variable that was in the best subset of size 1 (for this example all the subsets are nested).",
        "fact_type": "property",
        "importance_rank": 4,
        "paragraph_id": 4767,
        "page_number": 75
      },
      {
        "fact_text": "typically we choose the smallest model that minimizes an estimate of the expected prediction error.",
        "fact_type": "intuition",
        "importance_rank": 5,
        "paragraph_id": 4767,
        "page_number": 75
      }
    ]
  },
  {
    "concept_id": 144,
    "concept_name": "forward stepwise selection",
    "facts": [
      {
        "fact_text": "A linear regression model assumes that the regression function E(Y |X) is linear in the inputs X1, . . . , Xp. Linear models were largely developed in the precomputer age of statistics, but even in today\u2019s computer era there are still good reasons to study and use them.",
        "fact_type": "intuition",
        "importance_rank": 1,
        "paragraph_id": 4520,
        "page_number": 61
      },
      {
        "fact_text": "For prediction purposes they can sometimes outperform fancier nonlinear models, especially in situations with small numbers of training cases, low signal-to-noise ratio or sparse data.",
        "fact_type": "property",
        "importance_rank": 2,
        "paragraph_id": 4520,
        "page_number": 61
      }
    ]
  },
  {
    "concept_id": 150,
    "concept_name": "basis pursuit",
    "facts": [
      {
        "fact_text": "In the signal processing literature, the lasso is also known as basis pursuit (Chen et al., 1998).",
        "fact_type": "definition",
        "importance_rank": 1,
        "paragraph_id": 5118,
        "page_number": 86
      },
      {
        "fact_text": "lasso-type penalties were proposed in the basis pursuit method for signal processing (Chen et al., 1998).",
        "fact_type": "property",
        "importance_rank": 2,
        "paragraph_id": 5481,
        "page_number": 112
      },
      {
        "fact_text": "Just as in ridge regression, we can re-parametrize the constant \u03b20 by standardizing the predictors; the solution for \u02c6\u03b20 is \u00afy, and thereafter we fit a model without an intercept (Exercise 3.5). In the signal processing literature, the lasso is also known as basis pursuit (Chen et al., 1998).",
        "fact_type": "property",
        "importance_rank": 3,
        "paragraph_id": 5118,
        "page_number": 86
      }
    ]
  },
  {
    "concept_id": 151,
    "concept_name": "soft thresholding",
    "facts": [
      {
        "fact_text": "We shrink the dkj toward zero using soft thresholding\nd\u2032\nkj = sign(dkj)(|dkj| \u2212\u0394)+;",
        "fact_type": "formula",
        "importance_rank": 1,
        "paragraph_id": 48536,
        "page_number": 671
      },
      {
        "fact_text": "This constant guards against large dkj values that arise from expression values near zero.",
        "fact_type": "intuition",
        "importance_rank": 2,
        "paragraph_id": 48536,
        "page_number": 671
      },
      {
        "fact_text": "Here S(t, \u03bb) = sign(t)(|t|\u2212\u03bb)+ is the soft-thresholding operator in Table 3.4 on page 71.",
        "fact_type": "formula",
        "importance_rank": 3,
        "paragraph_id": 5476,
        "page_number": 111
      }
    ]
  },
  {
    "concept_id": 155,
    "concept_name": "lar-lasso connection",
    "facts": [
      {
        "fact_text": "A linear regression model assumes that the regression function E(Y |X) is linear in the inputs X1, . . . , Xp.",
        "fact_type": "intuition",
        "importance_rank": 1,
        "paragraph_id": 4520,
        "page_number": 61
      },
      {
        "fact_text": "many nonlinear techniques are direct generalizations of the linear methods discussed here.",
        "fact_type": "intuition",
        "importance_rank": 2,
        "paragraph_id": 4520,
        "page_number": 61
      }
    ]
  },
  {
    "concept_id": 157,
    "concept_name": "degrees of freedom for adaptive fit",
    "facts": [
      {
        "fact_text": "A linear regression model assumes that the regression function E(Y |X) is linear in the inputs X1, . . . , Xp.",
        "fact_type": "intuition",
        "importance_rank": 1,
        "paragraph_id": 4520,
        "page_number": 61
      },
      {
        "fact_text": "For prediction purposes they can sometimes outperform fancier nonlinear models, especially in situations with small numbers of training cases, low signal-to-noise ratio or sparse data.",
        "fact_type": "property",
        "importance_rank": 2,
        "paragraph_id": 4520,
        "page_number": 61
      }
    ]
  },
  {
    "concept_id": 159,
    "concept_name": "partial least squares",
    "facts": [
      {
        "fact_text": "This technique also constructs a set of linear combinations of the inputs for regression, but unlike principal components regression it uses y (in addition to X) for this construction.",
        "fact_type": "definition",
        "importance_rank": 1,
        "paragraph_id": 5275,
        "page_number": 98
      },
      {
        "fact_text": "Like principal component regression, partial least squares (PLS) is not scale invariant, so we assume that each xj is standardized to have mean 0 and variance 1.",
        "fact_type": "property",
        "importance_rank": 2,
        "paragraph_id": 5275,
        "page_number": 98
      },
      {
        "fact_text": "PLS begins by computing \u02c6\u03d51j = \u27e8xj, y\u27e9for each j. From this we construct the derived input z1 = \u03a3j \u02c6\u03d51jxj, which is the first partial least squares direction. Hence in the construction of each zm, the inputs are weighted by the strength of their univariate effect on y.",
        "fact_type": "formula",
        "importance_rank": 3,
        "paragraph_id": 5275,
        "page_number": 98
      },
      {
        "fact_text": "partial least squares seeks directions that have high variance and have high correlation with the response, in contrast to principal components regression which keys only on high variance (Stone and Brooks, 1990; Frank and Friedman, 1993).",
        "fact_type": "comparison",
        "importance_rank": 4,
        "paragraph_id": 5287,
        "page_number": 99
      },
      {
        "fact_text": "If the input matrix X is orthogonal, then partial least squares finds the least squares estimates after m = 1 steps. Subsequent steps have no effect",
        "fact_type": "property",
        "importance_rank": 5,
        "paragraph_id": 5291,
        "page_number": 99
      },
      {
        "fact_text": "the variance aspect tends to dominate, and so partial least squares behaves much like ridge regression and principal components regression.",
        "fact_type": "comparison",
        "importance_rank": 6,
        "paragraph_id": 5291,
        "page_number": 99
      },
      {
        "fact_text": "partial least squares also tends to shrink the low-variance directions, but can actually inflate some of the higher variance directions. This can make PLS a little unstable, and cause it to have slightly higher prediction error compared to ridge regression.",
        "fact_type": "property",
        "importance_rank": 7,
        "paragraph_id": 5295,
        "page_number": 100
      }
    ]
  },
  {
    "concept_id": 162,
    "concept_name": "curds and whey",
    "facts": [
      {
        "fact_text": "A linear regression model assumes that the regression function E(Y |X) is linear in the inputs X1, . . . , Xp.",
        "fact_type": "intuition",
        "importance_rank": 1,
        "paragraph_id": 4520,
        "page_number": 61
      },
      {
        "fact_text": "For prediction purposes they can sometimes outperform fancier nonlinear models, especially in situations with small numbers of training cases, low signal-to-noise ratio or sparse data.",
        "fact_type": "property",
        "importance_rank": 2,
        "paragraph_id": 4520,
        "page_number": 61
      }
    ]
  },
  {
    "concept_id": 163,
    "concept_name": "incremental forward stagewise regression",
    "facts": [
      {
        "fact_text": "It generates a coefficient profile by repeatedly updating (by a small amount \u03f5) the coefficient of the variable most correlated with the current residuals.",
        "fact_type": "definition",
        "importance_rank": 1,
        "paragraph_id": 5389,
        "page_number": 105
      },
      {
        "fact_text": "If \u03b4j = \u27e8xj, r\u27e9(the least-squares coefficient of the residual on jth predictor), then this is exactly the usual forward stagewise procedure (FS) outlined in Section 3.3.3.",
        "fact_type": "formula",
        "importance_rank": 2,
        "paragraph_id": 5389,
        "page_number": 105
      },
      {
        "fact_text": "Consider the linear-regression version of the forward-stagewise boosting algorithm 16.1 proposed in Section 16.1 (page 608). It generates a coefficient profile by repeatedly updating (by a small amount \u03f5) the coefficient of the variable most correlated with the current residuals.",
        "fact_type": "property",
        "importance_rank": 3,
        "paragraph_id": 5389,
        "page_number": 105
      },
      {
        "fact_text": "Letting \u03f5 \u21920 gives the right panel of Figure 3.19, which in this case is identical to the lasso path in Figure 3.10. We call this limiting procedure infinitesimal forward stagewise regression or FS0.",
        "fact_type": "property",
        "importance_rank": 4,
        "paragraph_id": 5389,
        "page_number": 105
      },
      {
        "fact_text": "This procedure plays an important role in non-linear, adaptive methods like boosting (Chapters 10 and 16) and is the version of incremental forward stagewise regression that is most amenable to theoretical analysis.",
        "fact_type": "intuition",
        "importance_rank": 5,
        "paragraph_id": 5389,
        "page_number": 105
      }
    ]
  },
  {
    "concept_id": 164,
    "concept_name": "infinitesimal forward stagewise regression",
    "facts": [
      {
        "fact_text": "Letting \u03f5 \u21920 gives the right panel of Figure 3.19, which in this case is identical to the lasso path in Figure 3.10. We call this limiting procedure infinitesimal forward stagewise regression or FS0.",
        "fact_type": "definition",
        "importance_rank": 1,
        "paragraph_id": 5389,
        "page_number": 105
      },
      {
        "fact_text": "This procedure plays an important role in non-linear, adaptive methods like boosting (Chapters 10 and 16) and is the version of incremental forward stagewise regression that is most amenable to theoretical analysis.",
        "fact_type": "property",
        "importance_rank": 2,
        "paragraph_id": 5389,
        "page_number": 105
      },
      {
        "fact_text": "B\u00a8uhlmann and Hothorn (2008) refer to the same procedure as \u201cL2boost\u201d, because of its connections to boosting.",
        "fact_type": "definition",
        "importance_rank": 3,
        "paragraph_id": 5389,
        "page_number": 105
      }
    ]
  },
  {
    "concept_id": 165,
    "concept_name": "l2boost",
    "facts": [
      {
        "fact_text": "B\u00a8uhlmann and Hothorn (2008) refer to the same procedure as \u201cL2boost\u201d, because of its connections to boosting.",
        "fact_type": "definition",
        "importance_rank": 1,
        "paragraph_id": 5389,
        "page_number": 105
      },
      {
        "fact_text": "This procedure plays an important role in non-linear, adaptive methods like boosting (Chapters 10 and 16) and is the version of incremental forward stagewise regression that is most amenable to theoretical analysis.",
        "fact_type": "property",
        "importance_rank": 2,
        "paragraph_id": 5389,
        "page_number": 105
      },
      {
        "fact_text": "Letting \u03f5 \u21920 gives the right panel of Figure 3.19, which in this case is identical to the lasso path in Figure 3.10. We call this limiting procedure infinitesimal forward stagewise regression or FS0.",
        "fact_type": "property",
        "importance_rank": 3,
        "paragraph_id": 5389,
        "page_number": 105
      },
      {
        "fact_text": "It generates a coefficient profile by repeatedly updating (by a small amount \u03f5) the coefficient of the variable most correlated with the current residuals.",
        "fact_type": "intuition",
        "importance_rank": 4,
        "paragraph_id": 5389,
        "page_number": 105
      }
    ]
  },
  {
    "concept_id": 166,
    "concept_name": "dantzig selector",
    "facts": [
      {
        "fact_text": "They call the solution the Dantzig selector (DS). It can be written equivalently as",
        "fact_type": "definition",
        "importance_rank": 1,
        "paragraph_id": 5413,
        "page_number": 107
      },
      {
        "fact_text": "Here || \u00b7 ||\u221edenotes the L\u221enorm, the maximum absolute value of the components of the vector. In this form it resembles the lasso, replacing squared error loss by the maximum absolute value of its gradient.",
        "fact_type": "formula",
        "importance_rank": 2,
        "paragraph_id": 5415,
        "page_number": 107
      },
      {
        "fact_text": "Note that as t gets large, both procedures yield the least squares solution if N < p. If p \u2265N, they both yield the least squares solution with minimum L1 norm. However for smaller values of t, the DS procedure produces a different path of solutions than the lasso.",
        "fact_type": "comparison",
        "importance_rank": 3,
        "paragraph_id": 5415,
        "page_number": 107
      },
      {
        "fact_text": "Candes and Tao (2007) show that the solution to DS is a linear programming problem; hence the name Dantzig selector, in honor of the late",
        "fact_type": "property",
        "importance_rank": 4,
        "paragraph_id": 5415,
        "page_number": 107
      },
      {
        "fact_text": "The Dantzig selector instead tries to minimize the maximum inner product of the current residual with all the predictors.",
        "fact_type": "property",
        "importance_rank": 5,
        "paragraph_id": 5417,
        "page_number": 108
      },
      {
        "fact_text": "Efron et al. (2007) also show that DS can yield extremely erratic coefficient paths as the regularization parameter s is varied.",
        "fact_type": "property",
        "importance_rank": 6,
        "paragraph_id": 5417,
        "page_number": 108
      }
    ]
  },
  {
    "concept_id": 167,
    "concept_name": "grouped lasso",
    "facts": [
      {
        "fact_text": "In some problems, the predictors belong to pre-defined groups; for example genes that belong to the same biological pathway, or collections of indicator (dummy) variables for representing the levels of a categorical predictor. In this situation it may be desirable to shrink and select the members of a group together.",
        "fact_type": "definition",
        "importance_rank": 1,
        "paragraph_id": 5419,
        "page_number": 108
      },
      {
        "fact_text": "The grouped lasso is one way to achieve this. Suppose that the p predictors are divided into L groups, with p\u2113the number in group \u2113.",
        "fact_type": "definition",
        "importance_rank": 2,
        "paragraph_id": 5419,
        "page_number": 108
      },
      {
        "fact_text": "The same kind of algorithm can be applied to the elastic net, the grouped lasso and many other models in which the penalty is a sum of functions of the individual parameters (Friedman et al., 2008a).",
        "fact_type": "property",
        "importance_rank": 3,
        "paragraph_id": 5476,
        "page_number": 111
      },
      {
        "fact_text": "Here S(t, \u03bb) = sign(t)(|t|\u2212\u03bb)+ is the soft-thresholding operator in Table 3.4 on page 71. The first argument to S(\u00b7) is the simple least-squares coefficient of the partial residual on the standardized variable xij.",
        "fact_type": "formula",
        "importance_rank": 4,
        "paragraph_id": 5476,
        "page_number": 111
      }
    ]
  },
  {
    "concept_id": 168,
    "concept_name": "relaxed lasso",
    "facts": [
      {
        "fact_text": "one can use the lasso to select the set of non-zero predictors, and then apply the lasso again, but using only the selected predictors from the first step. This is known as the relaxed lasso (Meinshausen, 2007).",
        "fact_type": "definition",
        "importance_rank": 1,
        "paragraph_id": 5436,
        "page_number": 109
      },
      {
        "fact_text": "the lasso shrinkage causes the estimates of the non-zero coefficients to be biased towards zero, and in general they are not consistent.",
        "fact_type": "property",
        "importance_rank": 2,
        "paragraph_id": 5436,
        "page_number": 109
      },
      {
        "fact_text": "One approach for reducing this bias is to run the lasso to identify the set of non-zero coefficients, and then fit an unrestricted linear model to the selected set of features.",
        "fact_type": "property",
        "importance_rank": 3,
        "paragraph_id": 5436,
        "page_number": 109
      },
      {
        "fact_text": "The idea is to use cross-validation to estimate the initial penalty parameter for the lasso, and then again for a second penalty parameter applied to the selected set of predictors.",
        "fact_type": "intuition",
        "importance_rank": 4,
        "paragraph_id": 5436,
        "page_number": 109
      },
      {
        "fact_text": "Here S indexes the subset of features with non-zero coefficients in the true underlying model, and XS are the columns of X corresponding to those features.",
        "fact_type": "property",
        "importance_rank": 5,
        "paragraph_id": 5436,
        "page_number": 109
      }
    ]
  },
  {
    "concept_id": 169,
    "concept_name": "scad penalty",
    "facts": [
      {
        "fact_text": "The second term in square-braces reduces the amount of shrinkage in the lasso for larger values of \u03b2, with ultimately no shrinkage as a \u2192\u221e.",
        "fact_type": "property",
        "importance_rank": 1,
        "paragraph_id": 5443,
        "page_number": 110
      },
      {
        "fact_text": "for some a \u22652. The second term in square-braces reduces the amount of shrinkage in the lasso for larger values of \u03b2, with ultimately no shrinkage as a \u2192\u221e. Figure 3.20 shows the SCAD penalty, along with the lasso and",
        "fact_type": "formula",
        "importance_rank": 2,
        "paragraph_id": 5443,
        "page_number": 110
      }
    ]
  },
  {
    "concept_id": 170,
    "concept_name": "adaptive lasso",
    "facts": [
      {
        "fact_text": "The adaptive lasso (Zou, 2006) uses a weighted penalty of the form \u03a3p\nj=1 wj|\u03b2j| where wj = 1/|\u02c6\u03b2j|\u03bd, \u02c6\u03b2j is the ordinary least squares estimate and \u03bd > 0.",
        "fact_type": "definition",
        "importance_rank": 1,
        "paragraph_id": 5454,
        "page_number": 110
      },
      {
        "fact_text": "The adaptive lasso yields consistent estimates of the parameters while retaining the attractive convexity property of the lasso.",
        "fact_type": "property",
        "importance_rank": 2,
        "paragraph_id": 5454,
        "page_number": 110
      },
      {
        "fact_text": "This is a practical approximation to the |\u03b2|q penalties (q = 1\u2212\u03bd here) discussed in Section 3.4.3.",
        "fact_type": "property",
        "importance_rank": 3,
        "paragraph_id": 5454,
        "page_number": 110
      },
      {
        "fact_text": "|\u03b2|1\u2212\u03bd. However this criterion is non-convex, which is a drawback since it makes the computation much more difficult.",
        "fact_type": "comparison",
        "importance_rank": 4,
        "paragraph_id": 5454,
        "page_number": 110
      }
    ]
  },
  {
    "concept_id": 171,
    "concept_name": "pathwise coordinate descent",
    "facts": [
      {
        "fact_text": "Friedman et al. (2007a) use the pathwise coordinate descent method (Section 3.8.6) to solve the modified lasso problem at each stage.",
        "fact_type": "definition",
        "importance_rank": 1,
        "paragraph_id": 48290,
        "page_number": 654
      },
      {
        "fact_text": "Repeated iteration of (3.84)\u2014cycling through each variable in turn until convergence\u2014yields the lasso estimate \u02c6\u03b2(\u03bb).",
        "fact_type": "property",
        "importance_rank": 2,
        "paragraph_id": 5476,
        "page_number": 111
      },
      {
        "fact_text": "We start with the smallest value \u03bbmax for which \u02c6\u03b2(\u03bbmax) = 0, decrease it a little and cycle through the variables until convergence. Then \u03bb is decreased again and the process is repeated, using the previous solution as a \u201cwarm start\u201d for the new value of \u03bb.",
        "fact_type": "property",
        "importance_rank": 3,
        "paragraph_id": 5476,
        "page_number": 111
      },
      {
        "fact_text": "This can be faster than the LARS algorithm, especially in large problems. A key to its speed is the fact that the quantities in (3.84) can be updated quickly as j varies, and often the update is to leave \u02dc\u03b2j = 0.",
        "fact_type": "comparison",
        "importance_rank": 4,
        "paragraph_id": 5476,
        "page_number": 111
      },
      {
        "fact_text": "it delivers solutions over a grid of \u03bb values, rather than the entire solution path.",
        "fact_type": "property",
        "importance_rank": 5,
        "paragraph_id": 5476,
        "page_number": 111
      },
      {
        "fact_text": "The same kind of algorithm can be applied to the elastic net, the grouped lasso and many other models in which the penalty is a sum of functions of the individual parameters (Friedman et al., 2008a).",
        "fact_type": "property",
        "importance_rank": 6,
        "paragraph_id": 5476,
        "page_number": 111
      }
    ]
  },
  {
    "concept_id": 174,
    "concept_name": "variance-covariance matrix of least squares estimates",
    "facts": [
      {
        "fact_text": "A linear regression model assumes that the regression function E(Y |X) is linear in the inputs X1, . . . , Xp.",
        "fact_type": "definition",
        "importance_rank": 1,
        "paragraph_id": 4520,
        "page_number": 61
      },
      {
        "fact_text": "For prediction purposes they can sometimes outperform fancier nonlinear models, especially in situations with small numbers of training cases, low signal-to-noise ratio or sparse data.",
        "fact_type": "property",
        "importance_rank": 2,
        "paragraph_id": 4520,
        "page_number": 61
      }
    ]
  }
]
